core/__init__.py
core/admin.py
core/apps.py
core/managers.py
core/models.py
core/sistema.py
core/storage.py
core/tests.py
core/urls.py
core/views.py
core/migrations/0001_initial.py
core/migrations/0002_auto_20200625_0045.py
core/migrations/__init__.py
filial/__init__.py
filial/admin.py
filial/apps.py
filial/models.py
filial/tests.py
filial/views.py
filial/migrations/0001_initial.py
filial/migrations/0002_auto_20200625_0045.py
filial/migrations/__init__.py
log/__init__.py
log/admin.py
log/apps.py
log/middleware.py
log/models.py
log/tests.py
log/views.py
log/migrations/0001_initial.py
log/migrations/0002_auto_20200625_0045.py
log/migrations/__init__.py
usr/__init__.py
usr/admin.py
usr/apps.py
usr/models.py
usr/tests.py
usr/views.py
usr/migrations/0001_initial.py
usr/migrations/__init__.py
django_inteliger_test-0.0.21.dist-info/LICENSE
django_inteliger_test-0.0.21.dist-info/METADATA
django_inteliger_test-0.0.21.dist-info/WHEEL
django_inteliger_test-0.0.21.dist-info/top_level.txt
django_inteliger_test-0.0.21.dist-info/RECORD
